djangocms_opensystem/__init__.py
djangocms_opensystem/apps.py
djangocms_opensystem/cms_plugins.py
djangocms_opensystem/models.py
djangocms_opensystem/conf/__init__.py
djangocms_opensystem/conf/settings.py
djangocms_opensystem/locale/fr/LC_MESSAGES/django.mo
djangocms_opensystem/locale/fr/LC_MESSAGES/django.po
djangocms_opensystem/migrations/0001_initial.py
djangocms_opensystem/migrations/0001_initial.pyc
djangocms_opensystem/migrations/__init__.py
djangocms_opensystem/migrations/__init__.pyc
djangocms_opensystem/templates/djangocms_opensystem/widget.html
djangocms_opensystem-1.0.0.dist-info/LICENSE.txt
djangocms_opensystem-1.0.0.dist-info/METADATA
djangocms_opensystem-1.0.0.dist-info/WHEEL
djangocms_opensystem-1.0.0.dist-info/top_level.txt
djangocms_opensystem-1.0.0.dist-info/RECORD
