Metadata-Version: 2.1
Name: djangocms-opensystem
Version: 1.0.0
Summary: A plugin for Django CMS that displays OpenSystem widgets.
Home-page: https://gitlab.com/kapt/open-source/djangocms-opensystem
Author: Dev Kapt
Author-email: dev@kapt.mobi
License: UNKNOWN
Platform: UNKNOWN
Classifier: Environment :: Web Environment
Classifier: Framework :: Django
Classifier: Framework :: Django :: 2.2
Classifier: Intended Audience :: Developers
Classifier: License :: OSI Approved :: GNU General Public License v3 (GPLv3)
Classifier: Programming Language :: Python
Classifier: Programming Language :: Python :: 2
Classifier: Programming Language :: Python :: 2.7
Classifier: Topic :: Internet :: WWW/HTTP
Classifier: Topic :: Internet :: WWW/HTTP :: Dynamic Content
Requires-Dist: django (<3.0)
Requires-Dist: django-cms
